dexmotion_viz/__init__.py
dexmotion_viz/sapien_viz/__init__.py
dexmotion_viz/sapien_viz/annotator.py
dexmotion_viz/sapien_viz/movie_maker.py
dexmotion_viz/sapien_viz/recorder.py
dexmotion_viz/sapien_viz/sapien_utils.py
dexmotion_viz/sapien_viz/visualizer.py
dexmotion_viz/sapien_viz/component/collision_sphere_component.py
dexmotion_viz/sapien_viz/entity/visual_robot.py
dexmotion_viz/sapien_viz/struct/movie_state.py
dexmotion_viz/sapien_viz/window/articulation_window.py
dexmotion_viz/sapien_viz/window/collision_sphere_entity_window.py
dexmotion_viz/sapien_viz/window/motion_planning_window.py
dexmotion_viz/sapien_viz/window/movie_window.py
dexmotion_viz/sapien_viz/window/record_window.py
dexmotion_viz/utils/motion_utils.py
dexmotion_viz-0.2.0.dist-info/METADATA
dexmotion_viz-0.2.0.dist-info/WHEEL
dexmotion_viz-0.2.0.dist-info/RECORD
